sopel_xkcdb/__init__.py
sopel_xkcdb/plugin.py
sopel_xkcdb-0.1.0.dist-info/licenses/COPYING
sopel_xkcdb-0.1.0.dist-info/METADATA
sopel_xkcdb-0.1.0.dist-info/WHEEL
sopel_xkcdb-0.1.0.dist-info/entry_points.txt
sopel_xkcdb-0.1.0.dist-info/top_level.txt
sopel_xkcdb-0.1.0.dist-info/RECORD
