Metadata-Version: 2.4
Name: sopel-xkcdb
Version: 0.1.0
Summary: XKCDB quotes plugin for Sopel IRC bots
Author-email: dgw <dgw@technobabbl.es>
License: EFL-2.0
Project-URL: Homepage, https://github.com/dgw/sopel-xkcdb
Project-URL: Bug Tracker, https://github.com/dgw/sopel-xkcdb/issues
Keywords: sopel,plugin,bot,irc
Platform: Linux x86, x86-64
Classifier: Intended Audience :: Developers
Classifier: Intended Audience :: System Administrators
Classifier: License :: Eiffel Forum License (EFL)
Classifier: License :: OSI Approved :: Eiffel Forum License
Classifier: Topic :: Communications :: Chat :: Internet Relay Chat
Requires-Python: <4,>=3.8
License-File: COPYING
Requires-Dist: sopel>=8.0
Requires-Dist: requests
Requires-Dist: lxml~=5.0
Requires-Dist: cssselect~=1.0
Dynamic: license-file
